MiSiteBaimaoPeixunJiangyiV15/README.md
MiSiteBaimaoPeixunJiangyiV15/__init__.py
MiSiteBaimaoPeixunJiangyiV15/__main__.py
MiSiteBaimaoPeixunJiangyiV15/file.epub
MiSiteBaimaoPeixunJiangyiV15/index.html
MiSiteBaimaoPeixunJiangyiV15/css/__init__.py
MiSiteBaimaoPeixunJiangyiV15/css/annotations.css
MiSiteBaimaoPeixunJiangyiV15/css/main.css
MiSiteBaimaoPeixunJiangyiV15/css/normalize.css
MiSiteBaimaoPeixunJiangyiV15/css/popup.css
MiSiteBaimaoPeixunJiangyiV15/font/__init__.py
MiSiteBaimaoPeixunJiangyiV15/font/fontello.eot
MiSiteBaimaoPeixunJiangyiV15/font/fontello.svg
MiSiteBaimaoPeixunJiangyiV15/font/fontello.ttf
MiSiteBaimaoPeixunJiangyiV15/font/fontello.woff
MiSiteBaimaoPeixunJiangyiV15/img/__init__.py
MiSiteBaimaoPeixunJiangyiV15/img/annotator-glyph-sprite.png
MiSiteBaimaoPeixunJiangyiV15/img/annotator-icon-sprite.png
MiSiteBaimaoPeixunJiangyiV15/img/apple-touch-icon.png
MiSiteBaimaoPeixunJiangyiV15/img/cancelfullscreen.png
MiSiteBaimaoPeixunJiangyiV15/img/close.png
MiSiteBaimaoPeixunJiangyiV15/img/fullscreen.png
MiSiteBaimaoPeixunJiangyiV15/img/loader.gif
MiSiteBaimaoPeixunJiangyiV15/img/menu-icon.png
MiSiteBaimaoPeixunJiangyiV15/img/save.png
MiSiteBaimaoPeixunJiangyiV15/img/saved.png
MiSiteBaimaoPeixunJiangyiV15/img/settings-s.png
MiSiteBaimaoPeixunJiangyiV15/img/settings.png
MiSiteBaimaoPeixunJiangyiV15/img/star.png
MiSiteBaimaoPeixunJiangyiV15/js/__init__.py
MiSiteBaimaoPeixunJiangyiV15/js/epub.js
MiSiteBaimaoPeixunJiangyiV15/js/epub.min.js
MiSiteBaimaoPeixunJiangyiV15/js/epub.min.map
MiSiteBaimaoPeixunJiangyiV15/js/hooks.min.js
MiSiteBaimaoPeixunJiangyiV15/js/hooks.min.map
MiSiteBaimaoPeixunJiangyiV15/js/reader.js
MiSiteBaimaoPeixunJiangyiV15/js/reader.js.map
MiSiteBaimaoPeixunJiangyiV15/js/reader.min.js
MiSiteBaimaoPeixunJiangyiV15/js/reader.min.map
MiSiteBaimaoPeixunJiangyiV15/js/hooks/__init__.py
MiSiteBaimaoPeixunJiangyiV15/js/hooks/extensions/__init__.py
MiSiteBaimaoPeixunJiangyiV15/js/hooks/extensions/highlight.js
mi_site_baimao_peixun_jiangyi_v1_5-2024.3.2.0.dist-info/METADATA
mi_site_baimao_peixun_jiangyi_v1_5-2024.3.2.0.dist-info/WHEEL
mi_site_baimao_peixun_jiangyi_v1_5-2024.3.2.0.dist-info/entry_points.txt
mi_site_baimao_peixun_jiangyi_v1_5-2024.3.2.0.dist-info/top_level.txt
mi_site_baimao_peixun_jiangyi_v1_5-2024.3.2.0.dist-info/RECORD
